LICENSE.txt
MANIFEST.in
README.rst
requirements.txt
setup.py
TestLiveServer.egg-info/PKG-INFO
TestLiveServer.egg-info/SOURCES.txt
TestLiveServer.egg-info/dependency_links.txt
TestLiveServer.egg-info/top_level.txt
liveandletdie/__init__.py